fds/__init__.py
fds/sdk/__init__.py
fds/sdk/AnalyticsDatastore/__init__.py
fds/sdk/AnalyticsDatastore/api_client.py
fds/sdk/AnalyticsDatastore/configuration.py
fds/sdk/AnalyticsDatastore/exceptions.py
fds/sdk/AnalyticsDatastore/model_utils.py
fds/sdk/AnalyticsDatastore/rest.py
fds/sdk/AnalyticsDatastore/api/__init__.py
fds/sdk/AnalyticsDatastore/api/documents_api.py
fds/sdk/AnalyticsDatastore/api/mappings_api.py
fds/sdk/AnalyticsDatastore/api/objects_api.py
fds/sdk/AnalyticsDatastore/apis/__init__.py
fds/sdk/AnalyticsDatastore/model/__init__.py
fds/sdk/AnalyticsDatastore/model/document_list_response.py
fds/sdk/AnalyticsDatastore/model/document_model.py
fds/sdk/AnalyticsDatastore/model/document_request.py
fds/sdk/AnalyticsDatastore/model/document_request_data.py
fds/sdk/AnalyticsDatastore/model/meta_model.py
fds/sdk/AnalyticsDatastore/model/meta_model_pagination.py
fds/sdk/AnalyticsDatastore/model/meta_request_model.py
fds/sdk/AnalyticsDatastore/model/meta_request_model_pagination.py
fds/sdk/AnalyticsDatastore/model/product_type_list_response.py
fds/sdk/AnalyticsDatastore/model/string_or_number_tag_value.py
fds/sdk/AnalyticsDatastore/model/tag_filter_model.py
fds/sdk/AnalyticsDatastore/model/tag_filter_model_data.py
fds/sdk/AnalyticsDatastore/model/tag_list_response.py
fds/sdk/AnalyticsDatastore/model/tag_model.py
fds/sdk/AnalyticsDatastore/model/tag_response.py
fds/sdk/AnalyticsDatastore/model/tag_values_list_response.py
fds/sdk/AnalyticsDatastore/models/__init__.py
fds.sdk.AnalyticsDatastore-0.22.7.dist-info/LICENSE
fds.sdk.AnalyticsDatastore-0.22.7.dist-info/METADATA
fds.sdk.AnalyticsDatastore-0.22.7.dist-info/WHEEL
fds.sdk.AnalyticsDatastore-0.22.7.dist-info/top_level.txt
fds.sdk.AnalyticsDatastore-0.22.7.dist-info/RECORD
